{
    "List" :[
             {
             "id": 107017,
             "time": "2015-08-23 12:21:24",
             "sbp": 99,
             "dbp": 56,
             "pulse": 70,
             "measureType": "H",
             "risk": 1
             },
             {
             "id": 108191,
             "time": "2015-08-25 09:25:59",
             "sbp": 122,
             "dbp": 74,
             "pulse": 74,
             "measureType": "S",
             "risk": 1
             },
             {
             "id": 110543,
             "time": "2015-08-28 22:19:08",
             "sbp": 130,
             "dbp": 81,
             "pulse": 90,
             "measureType": "S",
             "risk": 2
             },
             {
             "id": 110544,
             "time": "2015-08-28 22:21:43",
             "sbp": 96,
             "dbp": 64,
             "pulse": 53,
             "measureType": "S",
             "risk": 1
             },
             {
             "id": 110545,
             "time": "2015-08-28 22:24:19",
             "sbp": 96,
             "dbp": 76,
             "pulse": 66,
             "measureType": "S",
             "risk": 1
             },
             {
             "id": 110546,
             "time": "2015-08-28 22:25:31",
             "sbp": 110,
             "dbp": 63,
             "pulse": 67,
             "measureType": "S",
             "risk": 1
             },
             {
             "id": 110547,
             "time": "2015-08-28 22:28:07",
             "sbp": 83,
             "dbp": 59,
             "pulse": 57,
             "measureType": "S",
             "risk": 0
             }
             ]
}